setup.py
bin/noseline
nose_run_line_number/__init__.py
nose_run_line_number/plugin.py
nose_run_line_number.egg-info/PKG-INFO
nose_run_line_number.egg-info/SOURCES.txt
nose_run_line_number.egg-info/dependency_links.txt
nose_run_line_number.egg-info/entry_points.txt
nose_run_line_number.egg-info/top_level.txt