Metadata-Version: 1.0
Name: nose-run-line-number
Version: 0.0.1
Summary: Nose plugin to run tests by line number
Home-page: https://github.com/pitluga/nose-run-line-number
Author: Tony Pitluga
Author-email: tony.pitluga@gmail.com
License: MIT
Platform: UNKNOWN
